magento_2/__init__.py
magento_2/gui.py
magento_2/magento.py
magento_2-0.0.6.dist-info/METADATA
magento_2-0.0.6.dist-info/WHEEL
magento_2-0.0.6.dist-info/licenses/LICENSE
magento_2-0.0.6.dist-info/RECORD
