Metadata-Version: 2.3
Name: magento-2
Version: 0.0.6
Summary: A python module for interacting with the Magento 2 REST API. GUI
Project-URL: Homepage, https://github.com/Gunn1/Magento-2-API/tree/main
Project-URL: Issues, https://github.com/Gunn1/Magento-2-API/issues
Author-email: Gunn1 <tylerjgunn@gmail.com>
License-File: LICENSE
Classifier: License :: OSI Approved :: MIT License
Classifier: Operating System :: OS Independent
Classifier: Programming Language :: Python :: 3
Requires-Python: >=3.8
Requires-Dist: pandas
Requires-Dist: pysimplegui==4.60.5
Requires-Dist: python-dotenv
Requires-Dist: requests
